Lab_02/Src/Carga_completa.v
module CARGA_COMPLETA(
    input [3:0] A,
    input B,
    output Ea
);

assign  Ea = (A[3] & A[2] & A[1] & B);

endmodule

Practica_1/Carga_aceptable.v
module CARGA_ACEPTABLE(
    input [3:0] A,
    input B,
    output Ea
);
/*
*assign  Ea = ;
*/
assign Ea = ((B & A[2] & !A[1] & A[0]) | (B & !A[3] & A[2] & A[1]) | (B & A[3] & !A[1]) | (B & A[3] & !A[2]));

endmodule

Practica_1/Carga_regular.v
module CARGA_REGULAR(
    input [3:0] A,
    input B,
    output Ea
);

/*
*assign  Ea = ((A >= 4'b1100) & ((B == 1'b1) & (A < 4'b0101)));
*/
assign Ea = ((B & !A[3] & !A[1] & !A[0]) | (!B & A[3] & A[2]) | (B & !A[3] & !A[2]));

endmodule

Practica_1/Carga_baja.v
module CARGA_BAJA(
    input [3:0] A,
    input B,
    output Ea
);

/*
*assign  Ea = ((A >= 4'b1100) & ((B == 1'b1) & (A < 4'b0101)));
*/
assign Ea = ((!B & !A[3] & A[2]) | (!B & A[3] & !A[2]));

endmodule

Practica_1/Carga_critica.v
module CARGA_CRITICA(
    input [3:0] A,
    input B,
    output Ea
);

assign  Ea = !(A[3] || A[2] || B);

endmodule

Practica_1/Bateria_Descargada.v
module BATERIAS_DESCARGADAS(
    input [3:0] A,B,
    output Ea, Eb
);

assign  Ea = !(A[0] || A[1] || A[2] || A[3]);
assign  Eb = !(B[0] || B[1] || B[2] || B[3]);

endmodule

Practica_1/Sumador.v
module SUMADOR_4BITS(
    input [3:0] A,B,
    input Ci,
    output [3:0] Sum,
    output Co
);

assign {Co, Sum} = A + B + Ci;

endmodule

Practica_1/Monitor_de_carga_tb.v
`include "Bateria_Descargada.v"
`include "Carga_critica.v"
`include "Carga_baja.v"
`include "Carga_regular.v"
`include "Carga_aceptable.v"
`include "Carga_completa.v"
`include "Sumador.v"
`timescale 1ps/1ps

module Test1(
);

reg [3:0] A_tb;
reg [3:0] B_tb;
reg Ci_tb;

wire Ea_tb;
wire Eb_tb;
wire Ea2_tb;
wire Ea3_tb;
wire Ea4_tb;
wire Ea5_tb;
wire Ea6_tb;
wire [3:0] Sum_tb;
wire Co_tb;

SUMADOR_4BITS ut(
    .A(A_tb),
    .B(B_tb),
    .Ci(1'b0),
    .Sum(Sum_tb),
    .Co(Co_tb)
);

BATERIAS_DESCARGADAS uut(
    .A(A_tb),
    .B(B_tb),
    .Ea(Ea_tb),
    .Eb(Eb_tb)
);

CARGA_CRITICA uuut(
    .A(Sum_tb),
    .B(Co_tb),
    .Ea(Ea2_tb)
);

CARGA_BAJA uuuut(
    .A(Sum_tb),
    .B(Co_tb),
    .Ea(Ea3_tb)
);

CARGA_REGULAR uuuuut(
    .A(Sum_tb),
    .B(Co_tb),
    .Ea(Ea4_tb)
);

CARGA_ACEPTABLE uuuuuut(
    .A(Sum_tb),
    .B(Co_tb),
    .Ea(Ea5_tb)
);

CARGA_COMPLETA uuuuuuut (
    .A(Sum_tb),
    .B(Co_tb),
    .Ea(Ea6_tb)
);

initial begin
    A_tb = 4'b0000;
    B_tb = 4'b0000;
    #10;
    A_tb = 4'b0010;
    B_tb = 4'b0001;
    #10;
    A_tb = 4'b0100;
    B_tb = 4'b0101;
    #10;
    A_tb = 4'b0110;
    B_tb = 4'b0101;
    #10;
    A_tb = 4'b0000;
    B_tb = 4'b1100;
    #10;
    A_tb = 4'b1101;
    B_tb = 4'b0011;
    #10;
    A_tb = 4'b1111;
    B_tb = 4'b0110;
    #10;
    A_tb = 4'b1111;
    B_tb = 4'b0111;
    #10;
    A_tb = 4'b1111;
    B_tb = 4'b1111;
    #10;
end

initial begin:TEST_CASE
    $dumpfile("Test1.vcd");
    $dumpvars(-1, ut);
    $dumpvars(-1, uut);  
    $dumpvars(-1, uuut);  
    $dumpvars(-1, uuuut);
    $dumpvars(-1, uuuuut);
    $dumpvars(-1, uuuuuut);
    $dumpvars(-1, uuuuuuut);
    #100 $finish;
end

endmodule

Practica_1/build/Test1.vcd
$date
	Wed Dec  4 00:38:14 2024
$end
$version
	Icarus Verilog
$end
$timescale
	1ps
$end
$scope module Test1 $end
$scope module ut $end
$var wire 4 ! A [3:0] $end
$var wire 4 " B [3:0] $end
$var wire 1 # Ci $end
$var wire 4 $ Sum [3:0] $end
$var wire 1 % Co $end
$upscope $end
$upscope $end
$scope module Test1 $end
$scope module uut $end
$var wire 4 & A [3:0] $end
$var wire 4 ' B [3:0] $end
$var wire 1 ( Eb $end
$var wire 1 ) Ea $end
$upscope $end
$upscope $end
$scope module Test1 $end
$scope module uuut $end
$var wire 4 * A [3:0] $end
$var wire 1 % B $end
$var wire 1 + Ea $end
$upscope $end
$upscope $end
$scope module Test1 $end
$scope module uuuut $end
$var wire 4 , A [3:0] $end
$var wire 1 % B $end
$var wire 1 - Ea $end
$upscope $end
$upscope $end
$scope module Test1 $end
$scope module uuuuut $end
$var wire 4 . A [3:0] $end
$var wire 1 % B $end
$var wire 1 / Ea $end
$upscope $end
$upscope $end
$scope module Test1 $end
$scope module uuuuuut $end
$var wire 4 0 A [3:0] $end
$var wire 1 % B $end
$var wire 1 1 Ea $end
$upscope $end
$upscope $end
$scope module Test1 $end
$scope module uuuuuuut $end
$var wire 4 2 A [3:0] $end
$var wire 1 % B $end
$var wire 1 3 Ea $end
$upscope $end
$upscope $end
$enddefinitions $end
$comment Show the parameter values. $end
$dumpall
$end
#0
$dumpvars
03
b0 2
01
b0 0
0/
b0 .
0-
b0 ,
1+
b0 *
1)
1(
b0 '
b0 &
0%
b0 $
0#
b0 "
b0 !
$end
#10
0(
0)
b11 $
b11 *
b11 ,
b11 .
b11 0
b11 2
b1 "
b1 '
b10 !
b10 &
#20
1-
0+
b1001 $
b1001 *
b1001 ,
b1001 .
b1001 0
b1001 2
b101 "
b101 '
b100 !
b100 &
#30
b1011 $
b1011 *
b1011 ,
b1011 .
b1011 0
b1011 2
b110 !
b110 &
#40
1/
0-
1)
b1100 $
b1100 *
b1100 ,
b1100 .
b1100 0
b1100 2
b1100 "
b1100 '
b0 !
b0 &
#50
01
0(
0)
b0 $
b0 *
b0 ,
b0 .
b0 0
b0 2
1%
b11 "
b11 '
b1101 !
b1101 &
#60
11
0/
b101 $
b101 *
b101 ,
b101 .
b101 0
b101 2
b110 "
b110 '
b1111 !
b1111 &
#70
0/
b110 $
b110 *
b110 ,
b110 .
b110 0
b110 2
b111 "
b111 '
#80
01
13
b1110 $
b1110 *
b1110 ,
b1110 .
b1110 0
b1110 2
b1111 "
b1111 '
